jsonQ/__init__.py
jsonq-3.0.3.dist-info/licenses/LICENSE
jsonq-3.0.3.dist-info/METADATA
jsonq-3.0.3.dist-info/WHEEL
jsonq-3.0.3.dist-info/top_level.txt
jsonq-3.0.3.dist-info/RECORD
