Metadata-Version: 2.4
Name: jsonQ
Version: 3.0.3
Summary: A powerful Python library for querying JSON data with jQuery-like syntax
Author-email: Sriram Manikanth <msriram0803@gmail.com>
Project-URL: Homepage, https://github.com/Srirammkm/jsonQ
Project-URL: Bug Tracker, https://github.com/Srirammkm/jsonQ/issues
Project-URL: Documentation, https://github.com/Srirammkm/jsonQ#readme
Project-URL: Source Code, https://github.com/Srirammkm/jsonQ
Keywords: json,query,data,filter,search,nosql,database
Classifier: Development Status :: 5 - Production/Stable
Classifier: Intended Audience :: Developers
Classifier: Topic :: Software Development :: Libraries :: Python Modules
Classifier: Topic :: Database
Classifier: Topic :: Text Processing :: General
Classifier: Programming Language :: Python :: 3
Classifier: Programming Language :: Python :: 3.7
Classifier: Programming Language :: Python :: 3.8
Classifier: Programming Language :: Python :: 3.9
Classifier: Programming Language :: Python :: 3.10
Classifier: Programming Language :: Python :: 3.11
Classifier: Programming Language :: Python :: 3.12
Classifier: License :: OSI Approved :: MIT License
Classifier: Operating System :: OS Independent
Requires-Python: >=3.7
License-File: LICENSE
Dynamic: license-file
